vaesimca/__init__.py
vaesimca/vaesimca.py
vaesimca-1.1.0.dist-info/METADATA
vaesimca-1.1.0.dist-info/WHEEL
vaesimca-1.1.0.dist-info/licenses/LICENSE
vaesimca-1.1.0.dist-info/RECORD
