Metadata-Version: 2.4
Name: vaesimca
Version: 1.1.0
Summary: Implementation of VAESIMCA one class classification method
Project-URL: Homepage, https://github.com/svkucheryavski/vaesimca
Project-URL: Documentation, https://github.com/svkucheryavski/vaesimca
Project-URL: Repository, https://github.com/svkucheryavski/vaesimca
Project-URL: Bug Tracker, https://github.com/svkucheryavski/vaesimca/issues
Author-email: Sergey Kucheryavskiy <svkucheryavski@gmail.com>
License: MIT
License-File: LICENSE
Keywords: anomaly-detection,autoencoder,ddsimca,deep-learning,one-class-classification,pytorch,simca
Classifier: Development Status :: 5 - Production/Stable
Classifier: Intended Audience :: Science/Research
Classifier: License :: OSI Approved :: MIT License
Classifier: Operating System :: OS Independent
Classifier: Programming Language :: Python :: 3
Classifier: Programming Language :: Python :: 3.8
Classifier: Programming Language :: Python :: 3.9
Classifier: Programming Language :: Python :: 3.10
Classifier: Programming Language :: Python :: 3.11
Classifier: Programming Language :: Python :: 3.12
Classifier: Topic :: Scientific/Engineering :: Artificial Intelligence
Requires-Python: >=3.8
Requires-Dist: matplotlib>=3.3.0
Requires-Dist: numpy>=1.19.0
Requires-Dist: pandas>=1.2.0
Requires-Dist: pillow>=8.0.0
Requires-Dist: scipy>=1.6.0
Requires-Dist: torch-lr-finder>=0.2.1
Requires-Dist: torch>=1.9.0
Requires-Dist: torchvision>=0.10.0
Provides-Extra: dev
Requires-Dist: black>=22.0.0; extra == 'dev'
Requires-Dist: flake8>=4.0.0; extra == 'dev'
Requires-Dist: pytest-cov>=3.0.0; extra == 'dev'
Requires-Dist: pytest>=7.0.0; extra == 'dev'
